mlgos.cp39-win_amd64.pyd
mlgos-0.1.2.dist-info/METADATA
mlgos-0.1.2.dist-info/WHEEL
mlgos-0.1.2.dist-info/licenses/LICENSE
mlgos-0.1.2.dist-info/RECORD
