Metadata-Version: 2.2
Name: mlgos
Version: 0.1.2
Summary: A C++ linear regression extension using pybind11
Author-Email: SIV RAAM KRISHNAN K V <sivraamkrishnankv@gmail.com>
Requires-Python: >=3.8
